{
  "sites": [
    {
      "AZONOSITO": "SITE-001-BP",
      "MEGNEVEZES": "Duna Raktárbázis",
      "MEGNEVEZES_ANGOL": "Danube Warehouse Base",
      "TIPUS": "Raktár",
      "REGIO": "Közép-Magyarország",
      "VARMEGYE": "Pest",
      "TELEPULES": "Budapest",
      "IRSZ": "1095",
      "MIGRALT": true,
      "MERET": 1500,
      "MEGJEGYZES": "Központi raktárbázis a Duna mellett"
    },
    {
      "AZONOSITO": "SITE-002-DB",
      "MEGNEVEZES": "Hajdú Business Center",
      "MEGNEVEZES_ANGOL": "Hajdu Business Center",
      "TIPUS": "Iroda",
      "REGIO": "Észak-Alföld",
      "VARMEGYE": "Hajdú-Bihar",
      "TELEPULES": "Debrecen",
      "IRSZ": "4025",
      "MIGRALT": true,
      "MERET": 800,
      "MEGJEGYZES": "Modern irodaház a belvárosban"
    },
    {
      "AZONOSITO": "SITE-003-MI",
      "MEGNEVEZES": "Avas Ipari Park",
      "MEGNEVEZES_ANGOL": "Avas Industrial Park",
      "TIPUS": "Gyártóüzem",
      "REGIO": "Észak-Magyarország",
      "VARMEGYE": "Borsod-Abaúj-Zemplén",
      "TELEPULES": "Miskolc",
      "IRSZ": "3529",
      "MIGRALT": true,
      "MERET": 3000,
      "MEGJEGYZES": "Nagy kapacitású gyártóüzem"
    },
    {
      "AZONOSITO": "SITE-004-PE",
      "MEGNEVEZES": "Mecsek Logisztika",
      "MEGNEVEZES_ANGOL": "Mecsek Logistics",
      "TIPUS": "Raktár",
      "REGIO": "Dél-Dunántúl",
      "VARMEGYE": "Baranya",
      "TELEPULES": "Pécs",
      "IRSZ": "7621",
      "MIGRALT": true,
      "MERET": 1200,
      "MEGJEGYZES": "Regionális raktárbázis"
    },
    {
      "AZONOSITO": "SITE-005-SZ",
      "MEGNEVEZES": "Tisza Cargo Center",
      "MEGNEVEZES_ANGOL": "Tisza Cargo Center",
      "TIPUS": "Logisztikai központ",
      "REGIO": "Dél-Alföld",
      "VARMEGYE": "Csongrád-Csanád",
      "TELEPULES": "Szeged",
      "IRSZ": "6721",
      "MIGRALT": true,
      "MERET": 2500,
      "MEGJEGYZES": "Nemzetközi szállítmányozási központ"
    },
    {
      "AZONOSITO": "SITE-006-GY",
      "MEGNEVEZES": "Rába Raktár Komplexum",
      "MEGNEVEZES_ANGOL": "Raba Warehouse Complex",
      "TIPUS": "Raktár",
      "REGIO": "Nyugat-Dunántúl",
      "VARMEGYE": "Győr-Moson-Sopron",
      "TELEPULES": "Győr",
      "IRSZ": "9021",
      "MIGRALT": true,
      "MERET": 1800,
      "MEGJEGYZES": "Autóipari alkatrészek raktára"
    },
    {
      "AZONOSITO": "SITE-007-SH",
      "MEGNEVEZES": "Savaria Irodaház",
      "MEGNEVEZES_ANGOL": "Savaria Office Building",
      "TIPUS": "Iroda",
      "REGIO": "Nyugat-Dunántúl",
      "VARMEGYE": "Vas",
      "TELEPULES": "Szombathely",
      "IRSZ": "9700",
      "MIGRALT": true,
      "MERET": 650,
      "MEGJEGYZES": "Történelmi belvárosban található irodaház"
    },
    {
      "AZONOSITO": "SITE-008-ZE",
      "MEGNEVEZES": "Zala Ipari Centrum",
      "MEGNEVEZES_ANGOL": "Zala Industrial Center",
      "TIPUS": "Gyártóüzem",
      "REGIO": "Nyugat-Dunántúl",
      "VARMEGYE": "Zala",
      "TELEPULES": "Zalaegerszeg",
      "IRSZ": "8900",
      "MIGRALT": true,
      "MERET": 2800,
      "MEGJEGYZES": "Járműipari tesztpálya közelében"
    },
    {
      "AZONOSITO": "SITE-009-KV",
      "MEGNEVEZES": "Kapos Logisztikai Park",
      "MEGNEVEZES_ANGOL": "Kapos Logistics Park",
      "TIPUS": "Logisztikai központ",
      "REGIO": "Dél-Dunántúl",
      "VARMEGYE": "Somogy",
      "TELEPULES": "Kaposvár",
      "IRSZ": "7400",
      "MIGRALT": true,
      "MERET": 2200,
      "MEGJEGYZES": "Regionális elosztóközpont"
    },
    {
      "AZONOSITO": "SITE-010-SZ",
      "MEGNEVEZES": "Gemenc Raktárbázis",
      "MEGNEVEZES_ANGOL": "Gemenc Warehouse Base",
      "TIPUS": "Raktár",
      "REGIO": "Dél-Dunántúl",
      "VARMEGYE": "Tolna",
      "TELEPULES": "Szekszárd",
      "IRSZ": "7100",
      "MIGRALT": true,
      "MERET": 1100,
      "MEGJEGYZES": "Borászati termékek raktára"
    },
    {
      "AZONOSITO": "SITE-011-SF",
      "MEGNEVEZES": "Korona Üzletközpont",
      "MEGNEVEZES_ANGOL": "Crown Business Center",
      "TIPUS": "Iroda",
      "REGIO": "Közép-Dunántúl",
      "VARMEGYE": "Fejér",
      "TELEPULES": "Székesfehérvár",
      "IRSZ": "8000",
      "MIGRALT": true,
      "MERET": 750,
      "MEGJEGYZES": "Multifunkciós irodaház és üzletközpont"
    },
    {
      "AZONOSITO": "SITE-012-VP",
      "MEGNEVEZES": "Bakony Ipari Park",
      "MEGNEVEZES_ANGOL": "Bakony Industrial Park",
      "TIPUS": "Gyártóüzem",
      "REGIO": "Közép-Dunántúl",
      "VARMEGYE": "Veszprém",
      "TELEPULES": "Veszprém",
      "IRSZ": "8200",
      "MIGRALT": true,
      "MERET": 3200,
      "MEGJEGYZES": "Vegyipari gyártóüzem"
    },
    {
      "AZONOSITO": "SITE-013-TB",
      "MEGNEVEZES": "Turul Raktártelep",
      "MEGNEVEZES_ANGOL": "Turul Warehouse Complex",
      "TIPUS": "Raktár",
      "REGIO": "Közép-Dunántúl",
      "VARMEGYE": "Komárom-Esztergom",
      "TELEPULES": "Tatabánya",
      "IRSZ": "2800",
      "MIGRALT": true,
      "MERET": 1400,
      "MEGJEGYZES": "Ipari park területén található raktárbázis"
    },
    {
      "AZONOSITO": "SITE-014-ER",
      "MEGNEVEZES": "Érd-Parkváros Logisztikai Központ",
      "MEGNEVEZES_ANGOL": "Erd-Parktown Logistics Center",
      "TIPUS": "Logisztikai központ",
      "REGIO": "Közép-Magyarország",
      "VARMEGYE": "Pest",
      "TELEPULES": "Érd",
      "IRSZ": "2030",
      "MIGRALT": true,
      "MERET": 2100,
      "MEGJEGYZES": "Budapest agglomerációjában található központ"
    },
    {
      "AZONOSITO": "SITE-015-ST",
      "MEGNEVEZES": "Karancs Irodaház",
      "MEGNEVEZES_ANGOL": "Karancs Office Building",
      "TIPUS": "Iroda",
      "REGIO": "Észak-Magyarország",
      "VARMEGYE": "Nógrád",
      "TELEPULES": "Salgótarján",
      "IRSZ": "3100",
      "MIGRALT": true,
      "MERET": 600,
      "MEGJEGYZES": "Felújított irodaház a városközpontban"
    },
    {
      "AZONOSITO": "SITE-016-EG",
      "MEGNEVEZES": "Dobó Ipari Centrum",
      "MEGNEVEZES_ANGOL": "Dobo Industrial Center",
      "TIPUS": "Gyártóüzem",
      "REGIO": "Észak-Magyarország",
      "VARMEGYE": "Heves",
      "TELEPULES": "Eger",
      "IRSZ": "3300",
      "MIGRALT": true,
      "MERET": 2900,
      "MEGJEGYZES": "Elektronikai alkatrészek gyártása"
    },
    {
      "AZONOSITO": "SITE-017-SZ",
      "MEGNEVEZES": "Tisza-parti Raktárbázis",
      "MEGNEVEZES_ANGOL": "Tisza Riverside Warehouse",
      "TIPUS": "Raktár",
      "REGIO": "Észak-Alföld",
      "VARMEGYE": "Jász-Nagykun-Szolnok",
      "TELEPULES": "Szolnok",
      "IRSZ": "5000",
      "MIGRALT": true,
      "MERET": 1300,
      "MEGJEGYZES": "Folyami szállítási lehetőséggel"
    },
    {
      "AZONOSITO": "SITE-018-BC",
      "MEGNEVEZES": "Munkácsy Business Center",
      "MEGNEVEZES_ANGOL": "Munkacsy Business Center",
      "TIPUS": "Iroda",
      "REGIO": "Dél-Alföld",
      "VARMEGYE": "Békés",
      "TELEPULES": "Békéscsaba",
      "IRSZ": "5600",
      "MIGRALT": true,
      "MERET": 720,
      "MEGJEGYZES": "Modern irodaház a belvárosban"
    },
    {
      "AZONOSITO": "SITE-019-KM",
      "MEGNEVEZES": "Hírös Logisztikai Park",
      "MEGNEVEZES_ANGOL": "Hiros Logistics Park",
      "TIPUS": "Logisztikai központ",
      "REGIO": "Dél-Alföld",
      "VARMEGYE": "Bács-Kiskun",
      "TELEPULES": "Kecskemét",
      "IRSZ": "6000",
      "MIGRALT": true,
      "MERET": 2400,
      "MEGJEGYZES": "Autóipari beszállítók központja"
    },
    {
      "AZONOSITO": "SITE-020-NY",
      "MEGNEVEZES": "Nyírség Ipari Centrum",
      "MEGNEVEZES_ANGOL": "Nyirseg Industrial Center",
      "TIPUS": "Gyártóüzem",
      "REGIO": "Észak-Alföld",
      "VARMEGYE": "Szabolcs-Szatmár-Bereg",
      "TELEPULES": "Nyíregyháza",
      "IRSZ": "4400",
      "MIGRALT": true,
      "MERET": 3100,
      "MEGJEGYZES": "Gumiipari termékek gyártása"
    },
    {
      "AZONOSITO": "SITE-021-GO",
      "MEGNEVEZES": "Grassalkovich Raktárbázis",
      "MEGNEVEZES_ANGOL": "Grassalkovich Warehouse Base",
      "TIPUS": "Raktár",
      "REGIO": "Közép-Magyarország",
      "VARMEGYE": "Pest",
      "TELEPULES": "Gödöllő",
      "IRSZ": "2100",
      "MIGRALT": true,
      "MERET": 1250,
      "MEGJEGYZES": "Mezőgazdasági termékek raktára"
    },
    {
      "AZONOSITO": "SITE-022-SE",
      "MEGNEVEZES": "Dunakanyar Irodaház",
      "MEGNEVEZES_ANGOL": "Danube Bend Office Building",
      "TIPUS": "Iroda",
      "REGIO": "Közép-Magyarország",
      "VARMEGYE": "Pest",
      "TELEPULES": "Szentendre",
      "IRSZ": "2000",
      "MIGRALT": true,
      "MERET": 580,
      "MEGJEGYZES": "Művészeti központ közelében"
    },
    {
      "AZONOSITO": "SITE-023-HS",
      "MEGNEVEZES": "Hajdúsági Ipari Park",
      "MEGNEVEZES_ANGOL": "Hajdusag Industrial Park",
      "TIPUS": "Gyártóüzem",
      "REGIO": "Észak-Alföld",
      "VARMEGYE": "Hajdú-Bihar",
      "TELEPULES": "Hajdúszoboszló",
      "IRSZ": "4200",
      "MIGRALT": true,
      "MERET": 2700,
      "MEGJEGYZES": "Élelmiszeripari termékek gyártása"
    },
    {
      "AZONOSITO": "SITE-024-HM",
      "MEGNEVEZES": "Hódtó Raktárkomplexum",
      "MEGNEVEZES_ANGOL": "Hodto Warehouse Complex",
      "TIPUS": "Raktár",
      "REGIO": "Dél-Alföld",
      "VARMEGYE": "Csongrád-Csanád",
      "TELEPULES": "Hódmezővásárhely",
      "IRSZ": "6800",
      "MIGRALT": true,
      "MERET": 1350,
      "MEGJEGYZES": "Kerámiaipari termékek raktára"
    },
    {
      "AZONOSITO": "SITE-025-MO",
      "MEGNEVEZES": "Duna-Dráva Logisztikai Központ",
      "MEGNEVEZES_ANGOL": "Danube-Drava Logistics Center",
      "TIPUS": "Logisztikai központ",
      "REGIO": "Dél-Dunántúl",
      "VARMEGYE": "Baranya",
      "TELEPULES": "Mohács",
      "IRSZ": "7700",
      "MIGRALT": true,
      "MERET": 2300,
      "MEGJEGYZES": "Folyami kikötővel rendelkező központ"
    },
    {
      "AZONOSITO": "SITE-026-KB",
      "MEGNEVEZES": "BorsodChem Irodaház",
      "MEGNEVEZES_ANGOL": "BorsodChem Office Building",
      "TIPUS": "Iroda",
      "REGIO": "Észak-Magyarország",
      "VARMEGYE": "Borsod-Abaúj-Zemplén",
      "TELEPULES": "Kazincbarcika",
      "IRSZ": "3700",
      "MIGRALT": true,
      "MERET": 680,
      "MEGJEGYZES": "Vegyipari vállalat központi irodája"
    },
    {
      "AZONOSITO": "SITE-027-SO",
      "MEGNEVEZES": "Lővér Ipari Park",
      "MEGNEVEZES_ANGOL": "Lover Industrial Park",
      "TIPUS": "Gyártóüzem",
      "REGIO": "Nyugat-Dunántúl",
      "VARMEGYE": "Győr-Moson-Sopron",
      "TELEPULES": "Sopron",
      "IRSZ": "9400",
      "MIGRALT": true,
      "MERET": 2950,
      "MEGJEGYZES": "Faipari termékek gyártása"
    },
    {
      "AZONOSITO": "SITE-028-BP",
      "MEGNEVEZES": "Csepel Raktárbázis",
      "MEGNEVEZES_ANGOL": "Csepel Warehouse Base",
      "TIPUS": "Raktár",
      "REGIO": "Közép-Magyarország",
      "VARMEGYE": "Pest",
      "TELEPULES": "Budapest",
      "IRSZ": "1211",
      "MIGRALT": false,
      "MERET": 2200,
      "MEGJEGYZES": "Kikötői raktárbázis"
    },
    {
      "AZONOSITO": "SITE-029-BP",
      "MEGNEVEZES": "Váci úti Irodafolyosó",
      "MEGNEVEZES_ANGOL": "Vaci Road Office Corridor",
      "TIPUS": "Iroda",
      "REGIO": "Közép-Magyarország",
      "VARMEGYE": "Pest",
      "TELEPULES": "Budapest",
      "IRSZ": "1138",
      "MIGRALT": false,
      "MERET": 1500,
      "MEGJEGYZES": "Modern irodakomplexum"
    },
    {
      "AZONOSITO": "SITE-030-BP",
      "MEGNEVEZES": "Újpesti Ipari Park",
      "MEGNEVEZES_ANGOL": "Ujpest Industrial Park",
      "TIPUS": "Gyártóüzem",
      "REGIO": "Közép-Magyarország",
      "VARMEGYE": "Pest",
      "TELEPULES": "Budapest",
      "IRSZ": "1045",
      "MIGRALT": false,
      "MERET": 3500,
      "MEGJEGYZES": "Elektronikai termékek gyártása"
    },
    {
      "AZONOSITO": "SITE-031-DB",
      "MEGNEVEZES": "Debreceni Logisztikai Központ",
      "MEGNEVEZES_ANGOL": "Debrecen Logistics Center",
      "TIPUS": "Logisztikai központ",
      "REGIO": "Észak-Alföld",
      "VARMEGYE": "Hajdú-Bihar",
      "TELEPULES": "Debrecen",
      "IRSZ": "4030",
      "MIGRALT": false,
      "MERET": 2800,
      "MEGJEGYZES": "Nemzetközi repülőtér közelében"
    },
    {
      "AZONOSITO": "SITE-032-MI",
      "MEGNEVEZES": "Diósgyőri Raktárbázis",
      "MEGNEVEZES_ANGOL": "Diosgyori Warehouse Base",
      "TIPUS": "Raktár",
      "REGIO": "Észak-Magyarország",
      "VARMEGYE": "Borsod-Abaúj-Zemplén",
      "TELEPULES": "Miskolc",
      "IRSZ": "3533",
      "MIGRALT": false,
      "MERET": 1600,
      "MEGJEGYZES": "Acélipari termékek raktára"
    },
    {
      "AZONOSITO": "SITE-033-PE",
      "MEGNEVEZES": "Pécsi Ipari Centrum",
      "MEGNEVEZES_ANGOL": "Pecs Industrial Center",
      "TIPUS": "Gyártóüzem",
      "REGIO": "Dél-Dunántúl",
      "VARMEGYE": "Baranya",
      "TELEPULES": "Pécs",
      "IRSZ": "7630",
      "MIGRALT": false,
      "MERET": 2600,
      "MEGJEGYZES": "Építőipari termékek gyártása"
    },
    {
      "AZONOSITO": "SITE-034-SZ",
      "MEGNEVEZES": "Szegedi Irodapark",
      "MEGNEVEZES_ANGOL": "Szeged Office Park",
      "TIPUS": "Iroda",
      "REGIO": "Dél-Alföld",
      "VARMEGYE": "Csongrád-Csanád",
      "TELEPULES": "Szeged",
      "IRSZ": "6724",
      "MIGRALT": false,
      "MERET": 900,
      "MEGJEGYZES": "Egyetem közelében található irodapark"
    },
    {
      "AZONOSITO": "SITE-035-GY",
      "MEGNEVEZES": "Győri Logisztikai Park",
      "MEGNEVEZES_ANGOL": "Gyor Logistics Park",
      "TIPUS": "Logisztikai központ",
      "REGIO": "Nyugat-Dunántúl",
      "VARMEGYE": "Győr-Moson-Sopron",
      "TELEPULES": "Győr",
      "IRSZ": "9027",
      "MIGRALT": false,
      "MERET": 2700,
      "MEGJEGYZES": "Autóipari beszállítók központja"
    },
    {
      "AZONOSITO": "SITE-036-SH",
      "MEGNEVEZES": "Szombathelyi Ipari Park",
      "MEGNEVEZES_ANGOL": "Szombathely Industrial Park",
      "TIPUS": "Gyártóüzem",
      "REGIO": "Nyugat-Dunántúl",
      "VARMEGYE": "Vas",
      "TELEPULES": "Szombathely",
      "IRSZ": "9700",
      "MIGRALT": false,
      "MERET": 3300,
      "MEGJEGYZES": "Elektronikai termékek gyártása"
    },
    {
      "AZONOSITO": "SITE-037-ZE",
      "MEGNEVEZES": "Zalaegerszegi Raktárbázis",
      "MEGNEVEZES_ANGOL": "Zalaegerszeg Warehouse Base",
      "TIPUS": "Raktár",
      "REGIO": "Nyugat-Dunántúl",
      "VARMEGYE": "Zala",
      "TELEPULES": "Zalaegerszeg",
      "IRSZ": "8900",
      "MIGRALT": false,
      "MERET": 1450,
      "MEGJEGYZES": "Járműipari alkatrészek raktára"
    },
    {
      "AZONOSITO": "SITE-038-KV",
      "MEGNEVEZES": "Kaposvári Irodaház",
      "MEGNEVEZES_ANGOL": "Kaposvar Office Building",
      "TIPUS": "Iroda",
      "REGIO": "Dél-Dunántúl",
      "VARMEGYE": "Somogy",
      "TELEPULES": "Kaposvár",
      "IRSZ": "7400",
      "MIGRALT": false,
      "MERET": 750,
      "MEGJEGYZES": "Felújított irodaház a belvárosban"
    },
    {
      "AZONOSITO": "SITE-039-SZ",
      "MEGNEVEZES": "Szekszárdi Ipari Park",
      "MEGNEVEZES_ANGOL": "Szekszard Industrial Park",
      "TIPUS": "Gyártóüzem",
      "REGIO": "Dél-Dunántúl",
      "VARMEGYE": "Tolna",
      "TELEPULES": "Szekszárd",
      "IRSZ": "7100",
      "MIGRALT": false,
      "MERET": 2500,
      "MEGJEGYZES": "Élelmiszeripari termékek gyártása"
    },
    {
      "AZONOSITO": "SITE-040-SF",
      "MEGNEVEZES": "Székesfehérvári Logisztikai Központ",
      "MEGNEVEZES_ANGOL": "Szekesfehervar Logistics Center",
      "TIPUS": "Logisztikai központ",
      "REGIO": "Közép-Dunántúl",
      "VARMEGYE": "Fejér",
      "TELEPULES": "Székesfehérvár",
      "IRSZ": "8000",
      "MIGRALT": false,
      "MERET": 2900,
      "MEGJEGYZES": "Elektronikai ipar kiszolgálása"
    },
    {
      "AZONOSITO": "SITE-041-VP",
      "MEGNEVEZES": "Veszprémi Raktárbázis",
      "MEGNEVEZES_ANGOL": "Veszprem Warehouse Base",
      "TIPUS": "Raktár",
      "REGIO": "Közép-Dunántúl",
      "VARMEGYE": "Veszprém",
      "TELEPULES": "Veszprém",
      "IRSZ": "8200",
      "MIGRALT": false,
      "MERET": 1350,
      "MEGJEGYZES": "Vegyipari termékek raktára"
    },
    {
      "AZONOSITO": "SITE-042-TB",
      "MEGNEVEZES": "Tatabányai Ipari Park",
      "MEGNEVEZES_ANGOL": "Tatabanya Industrial Park",
      "TIPUS": "Gyártóüzem",
      "REGIO": "Közép-Dunántúl",
      "VARMEGYE": "Komárom-Esztergom",
      "TELEPULES": "Tatabánya",
      "IRSZ": "2800",
      "MIGRALT": false,
      "MERET": 3400,
      "MEGJEGYZES": "Autóipari alkatrészek gyártása"
    },
    {
      "AZONOSITO": "SITE-043-ER",
      "MEGNEVEZES": "Érdi Irodaház",
      "MEGNEVEZES_ANGOL": "Erd Office Building",
      "TIPUS": "Iroda",
      "REGIO": "Közép-Magyarország",
      "VARMEGYE": "Pest",
      "TELEPULES": "Érd",
      "IRSZ": "2030",
      "MIGRALT": false,
      "MERET": 680,
      "MEGJEGYZES": "Modern irodaház az M7 autópálya közelében"
    },
    {
      "AZONOSITO": "SITE-044-ST",
      "MEGNEVEZES": "Salgótarjáni Ipari Park",
      "MEGNEVEZES_ANGOL": "Salgotarjan Industrial Park",
      "TIPUS": "Gyártóüzem",
      "REGIO": "Észak-Magyarország",
      "VARMEGYE": "Nógrád",
      "TELEPULES": "Salgótarján",
      "IRSZ": "3100",
      "MIGRALT": false,
      "MERET": 2200,
      "MEGJEGYZES": "Fémipari termékek gyártása"
    },
    {
      "AZONOSITO": "SITE-045-EG",
      "MEGNEVEZES": "Egri Logisztikai Központ",
      "MEGNEVEZES_ANGOL": "Eger Logistics Center",
      "TIPUS": "Logisztikai központ",
      "REGIO": "Észak-Magyarország",
      "VARMEGYE": "Heves",
      "TELEPULES": "Eger",
      "IRSZ": "3300",
      "MIGRALT": false,
      "MERET": 2100,
      "MEGJEGYZES": "Regionális elosztóközpont"
    },
    {
      "AZONOSITO": "SITE-046-SZ",
      "MEGNEVEZES": "Szolnoki Irodaház",
      "MEGNEVEZES_ANGOL": "Szolnok Office Building",
      "TIPUS": "Iroda",
      "REGIO": "Észak-Alföld",
      "VARMEGYE": "Jász-Nagykun-Szolnok",
      "TELEPULES": "Szolnok",
      "IRSZ": "5000",
      "MIGRALT": false,
      "MERET": 620,
      "MEGJEGYZES": "Tisza-parti irodaház"
    },
    {
      "AZONOSITO": "SITE-047-BC",
      "MEGNEVEZES": "Békéscsabai Ipari Park",
      "MEGNEVEZES_ANGOL": "Bekescsaba Industrial Park",
      "TIPUS": "Gyártóüzem",
      "REGIO": "Dél-Alföld",
      "VARMEGYE": "Békés",
      "TELEPULES": "Békéscsaba",
      "IRSZ": "5600",
      "MIGRALT": false,
      "MERET": 2800,
      "MEGJEGYZES": "Élelmiszeripari termékek gyártása"
    },
    {
      "AZONOSITO": "SITE-048-KM",
      "MEGNEVEZES": "Kecskeméti Raktárbázis",
      "MEGNEVEZES_ANGOL": "Kecskemet Warehouse Base",
      "TIPUS": "Raktár",
      "REGIO": "Dél-Alföld",
      "VARMEGYE": "Bács-Kiskun",
      "TELEPULES": "Kecskemét",
      "IRSZ": "6000",
      "MIGRALT": false,
      "MERET": 1800,
      "MEGJEGYZES": "Autóipari alkatrészek raktára"
    },
    {
      "AZONOSITO": "SITE-049-NY",
      "MEGNEVEZES": "Nyíregyházi Logisztikai Központ",
      "MEGNEVEZES_ANGOL": "Nyiregyhaza Logistics Center",
      "TIPUS": "Logisztikai központ",
      "REGIO": "Észak-Alföld",
      "VARMEGYE": "Szabolcs-Szatmár-Bereg",
      "TELEPULES": "Nyíregyháza",
      "IRSZ": "4400",
      "MIGRALT": false,
      "MERET": 2600,
      "MEGJEGYZES": "Ukrán határ közeli logisztikai központ"
    },
    {
      "AZONOSITO": "SITE-050-GO",
      "MEGNEVEZES": "Gödöllői Ipari Park",
      "MEGNEVEZES_ANGOL": "Godollo Industrial Park",
      "TIPUS": "Gyártóüzem",
      "REGIO": "Közép-Magyarország",
      "VARMEGYE": "Pest",
      "TELEPULES": "Gödöllő",
      "IRSZ": "2100",
      "MIGRALT": false,
      "MERET": 2900,
      "MEGJEGYZES": "Mezőgazdasági gépek gyártása"
    },
    {
      "AZONOSITO": "SITE-051-SE",
      "MEGNEVEZES": "Szentendrei Raktárbázis",
      "MEGNEVEZES_ANGOL": "Szentendre Warehouse Base",
      "TIPUS": "Raktár",
      "REGIO": "Közép-Magyarország",
      "VARMEGYE": "Pest",
      "TELEPULES": "Szentendre",
      "IRSZ": "2000",
      "MIGRALT": false,
      "MERET": 1100,
      "MEGJEGYZES": "Művészeti termékek raktára"
    },
    {
      "AZONOSITO": "SITE-052-HS",
      "MEGNEVEZES": "Hajdúszoboszlói Irodaház",
      "MEGNEVEZES_ANGOL": "Hajduszoboszlo Office Building",
      "TIPUS": "Iroda",
      "REGIO": "Észak-Alföld",
      "VARMEGYE": "Hajdú-Bihar",
      "TELEPULES": "Hajdúszoboszló",
      "IRSZ": "4200",
      "MIGRALT": false,
      "MERET": 550,
      "MEGJEGYZES": "Turisztikai szolgáltatások irodaháza"
    },
    {
      "AZONOSITO": "SITE-053-HM",
      "MEGNEVEZES": "Hódmezővásárhelyi Ipari Park",
      "MEGNEVEZES_ANGOL": "Hodmezovasarhely Industrial Park",
      "TIPUS": "Gyártóüzem",
      "REGIO": "Dél-Alföld",
      "VARMEGYE": "Csongrád-Csanád",
      "TELEPULES": "Hódmezővásárhely",
      "IRSZ": "6800",
      "MIGRALT": false,
      "MERET": 2700,
      "MEGJEGYZES": "Kerámiaipari termékek gyártása"
    },
    {
      "AZONOSITO": "SITE-054-MO",
      "MEGNEVEZES": "Mohácsi Raktárbázis",
      "MEGNEVEZES_ANGOL": "Mohacs Warehouse Base",
      "TIPUS": "Raktár",
      "REGIO": "Dél-Dunántúl",
      "VARMEGYE": "Baranya",
      "TELEPULES": "Mohács",
      "IRSZ": "7700",
      "MIGRALT": false,
      "MERET": 1250,
      "MEGJEGYZES": "Folyami kikötővel rendelkező raktár"
    },
    {
      "AZONOSITO": "SITE-055-KB",
      "MEGNEVEZES": "Kazincbarcikai Ipari Park",
      "MEGNEVEZES_ANGOL": "Kazincbarcika Industrial Park",
      "TIPUS": "Gyártóüzem",
      "REGIO": "Észak-Magyarország",
      "VARMEGYE": "Borsod-Abaúj-Zemplén",
      "TELEPULES": "Kazincbarcika",
      "IRSZ": "3700",
      "MIGRALT": false,
      "MERET": 3100,
      "MEGJEGYZES": "Vegyipari termékek gyártása"
    },
    {
      "AZONOSITO": "SITE-056-SO",
      "MEGNEVEZES": "Soproni Logisztikai Központ",
      "MEGNEVEZES_ANGOL": "Sopron Logistics Center",
      "TIPUS": "Logisztikai központ",
      "REGIO": "Nyugat-Dunántúl",
      "VARMEGYE": "Győr-Moson-Sopron",
      "TELEPULES": "Sopron",
      "IRSZ": "9400",
      "MIGRALT": false,
      "MERET": 2200,
      "MEGJEGYZES": "Osztrák határ közeli logisztikai központ"
    },
    {
      "AZONOSITO": "SITE-057-BP",
      "MEGNEVEZES": "Budaörsi Irodapark",
      "MEGNEVEZES_ANGOL": "Budaors Office Park",
      "TIPUS": "Iroda",
      "REGIO": "Közép-Magyarország",
      "VARMEGYE": "Pest",
      "TELEPULES": "Budaörs",
      "IRSZ": "2040",
      "MIGRALT": false,
      "MERET": 1200,
      "MEGJEGYZES": "Modern irodapark az M1-M7 autópálya mellett"
    },
    {
      "AZONOSITO": "SITE-058-DB",
      "MEGNEVEZES": "Debreceni Ipari Park",
      "MEGNEVEZES_ANGOL": "Debrecen Industrial Park",
      "TIPUS": "Gyártóüzem",
      "REGIO": "Észak-Alföld",
      "VARMEGYE": "Hajdú-Bihar",
      "TELEPULES": "Debrecen",
      "IRSZ": "4031",
      "MIGRALT": false,
      "MERET": 3600,
      "MEGJEGYZES": "Elektronikai termékek gyártása"
    },
    {
      "AZONOSITO": "SITE-059-MI",
      "MEGNEVEZES": "Miskolci Logisztikai Központ",
      "MEGNEVEZES_ANGOL": "Miskolc Logistics Center",
      "TIPUS": "Logisztikai központ",
      "REGIO": "Észak-Magyarország",
      "VARMEGYE": "Borsod-Abaúj-Zemplén",
      "TELEPULES": "Miskolc",
      "IRSZ": "3526",
      "MIGRALT": false,
      "MERET": 2400,
      "MEGJEGYZES": "Regionális elosztóközpont"
    },
    {
      "AZONOSITO": "SITE-060-PE",
      "MEGNEVEZES": "Pécsi Irodaház",
      "MEGNEVEZES_ANGOL": "Pecs Office Building",
      "TIPUS": "Iroda",
      "REGIO": "Dél-Dunántúl",
      "VARMEGYE": "Baranya",
      "TELEPULES": "Pécs",
      "IRSZ": "7624",
      "MIGRALT": false,
      "MERET": 850,
      "MEGJEGYZES": "Egyetem közelében található irodaház"
    },
    {
      "AZONOSITO": "SITE-061-SZ",
      "MEGNEVEZES": "Szegedi Ipari Park",
      "MEGNEVEZES_ANGOL": "Szeged Industrial Park",
      "TIPUS": "Gyártóüzem",
      "REGIO": "Dél-Alföld",
      "VARMEGYE": "Csongrád-Csanád",
      "TELEPULES": "Szeged",
      "IRSZ": "6728",
      "MIGRALT": false,
      "MERET": 3200,
      "MEGJEGYZES": "Élelmiszeripari termékek gyártása"
    },
    {
      "AZONOSITO": "SITE-062-GY",
      "MEGNEVEZES": "Győri Raktárbázis",
      "MEGNEVEZES_ANGOL": "Gyor Warehouse Base",
      "TIPUS": "Raktár",
      "REGIO": "Nyugat-Dunántúl",
      "VARMEGYE": "Győr-Moson-Sopron",
      "TELEPULES": "Győr",
      "IRSZ": "9028",
      "MIGRALT": false,
      "MERET": 1700,
      "MEGJEGYZES": "Autóipari alkatrészek raktára"
    },
    {
      "AZONOSITO": "SITE-063-SH",
      "MEGNEVEZES": "Szombathelyi Logisztikai Központ",
      "MEGNEVEZES_ANGOL": "Szombathely Logistics Center",
      "TIPUS": "Logisztikai központ",
      "REGIO": "Nyugat-Dunántúl",
      "VARMEGYE": "Vas",
      "TELEPULES": "Szombathely",
      "IRSZ": "9700",
      "MIGRALT": false,
      "MERET": 2300,
      "MEGJEGYZES": "Osztrák határ közeli logisztikai központ"
    },
    {
      "AZONOSITO": "SITE-064-ZE",
      "MEGNEVEZES": "Zalaegerszegi Irodaház",
      "MEGNEVEZES_ANGOL": "Zalaegerszeg Office Building",
      "TIPUS": "Iroda",
      "REGIO": "Nyugat-Dunántúl",
      "VARMEGYE": "Zala",
      "TELEPULES": "Zalaegerszeg",
      "IRSZ": "8900",
      "MIGRALT": false,
      "MERET": 700,
      "MEGJEGYZES": "Modern irodaház a belvárosban"
    },
    {
      "AZONOSITO": "SITE-065-KV",
      "MEGNEVEZES": "Kaposvári Ipari Park",
      "MEGNEVEZES_ANGOL": "Kaposvar Industrial Park",
      "TIPUS": "Gyártóüzem",
      "REGIO": "Dél-Dunántúl",
      "VARMEGYE": "Somogy",
      "TELEPULES": "Kaposvár",
      "IRSZ": "7400",
      "MIGRALT": false,
      "MERET": 2600,
      "MEGJEGYZES": "Élelmiszeripari termékek gyártása"
    },
    {
      "AZONOSITO": "SITE-066-SZ",
      "MEGNEVEZES": "Szekszárdi Raktárbázis",
      "MEGNEVEZES_ANGOL": "Szekszard Warehouse Base",
      "TIPUS": "Raktár",
      "REGIO": "Dél-Dunántúl",
      "VARMEGYE": "Tolna",
      "TELEPULES": "Szekszárd",
      "IRSZ": "7100",
      "MIGRALT": false,
      "MERET": 1300,
      "MEGJEGYZES": "Borászati termékek raktára"
    },
    {
      "AZONOSITO": "SITE-067-SF",
      "MEGNEVEZES": "Székesfehérvári Ipari Park",
      "MEGNEVEZES_ANGOL": "Szekesfehervar Industrial Park",
      "TIPUS": "Gyártóüzem",
      "REGIO": "Közép-Dunántúl",
      "VARMEGYE": "Fejér",
      "TELEPULES": "Székesfehérvár",
      "IRSZ": "8000",
      "MIGRALT": false,
      "MERET": 3800,
      "MEGJEGYZES": "Elektronikai termékek gyártása"
    },
    {
      "AZONOSITO": "SITE-068-VP",
      "MEGNEVEZES": "Veszprémi Irodaház",
      "MEGNEVEZES_ANGOL": "Veszprem Office Building",
      "TIPUS": "Iroda",
      "REGIO": "Közép-Dunántúl",
      "VARMEGYE": "Veszprém",
      "TELEPULES": "Veszprém",
      "IRSZ": "8200",
      "MIGRALT": false,
      "MERET": 780,
      "MEGJEGYZES": "Egyetem közelében található irodaház"
    },
    {
      "AZONOSITO": "SITE-069-TB",
      "MEGNEVEZES": "Tatabányai Logisztikai Központ",
      "MEGNEVEZES_ANGOL": "Tatabanya Logistics Center",
      "TIPUS": "Logisztikai központ",
      "REGIO": "Közép-Dunántúl",
      "VARMEGYE": "Komárom-Esztergom",
      "TELEPULES": "Tatabánya",
      "IRSZ": "2800",
      "MIGRALT": false,
      "MERET": 2500,
      "MEGJEGYZES": "M1 autópálya melletti logisztikai központ"
    },
    {
      "AZONOSITO": "SITE-070-ER",
      "MEGNEVEZES": "Érdi Ipari Park",
      "MEGNEVEZES_ANGOL": "Erd Industrial Park",
      "TIPUS": "Gyártóüzem",
      "REGIO": "Közép-Magyarország",
      "VARMEGYE": "Pest",
      "TELEPULES": "Érd",
      "IRSZ": "2030",
      "MIGRALT": false,
      "MERET": 2400,
      "MEGJEGYZES": "Építőipari termékek gyártása"
    },
    {
      "AZONOSITO": "SITE-071-ST",
      "MEGNEVEZES": "Salgótarjáni Raktárbázis",
      "MEGNEVEZES_ANGOL": "Salgotarjan Warehouse Base",
      "TIPUS": "Raktár",
      "REGIO": "Észak-Magyarország",
      "VARMEGYE": "Nógrád",
      "TELEPULES": "Salgótarján",
      "IRSZ": "3100",
      "MIGRALT": false,
      "MERET": 1150,
      "MEGJEGYZES": "Fémipari termékek raktára"
    },
    {
      "AZONOSITO": "SITE-072-EG",
      "MEGNEVEZES": "Egri Irodaház",
      "MEGNEVEZES_ANGOL": "Eger Office Building",
      "TIPUS": "Iroda",
      "REGIO": "Észak-Magyarország",
      "VARMEGYE": "Heves",
      "TELEPULES": "Eger",
      "IRSZ": "3300",
      "MIGRALT": false,
      "MERET": 650,
      "MEGJEGYZES": "Történelmi belvárosban található irodaház"
    },
    {
      "AZONOSITO": "SITE-073-SZ",
      "MEGNEVEZES": "Szolnoki Ipari Park",
      "MEGNEVEZES_ANGOL": "Szolnok Industrial Park",
      "TIPUS": "Gyártóüzem",
      "REGIO": "Észak-Alföld",
      "VARMEGYE": "Jász-Nagykun-Szolnok",
      "TELEPULES": "Szolnok",
      "IRSZ": "5000",
      "MIGRALT": false,
      "MERET": 2800,
      "MEGJEGYZES": "Fémipari termékek gyártása"
    },
    {
      "AZONOSITO": "SITE-074-BC",
      "MEGNEVEZES": "Békéscsabai Logisztikai Központ",
      "MEGNEVEZES_ANGOL": "Bekescsaba Logistics Center",
      "TIPUS": "Logisztikai központ",
      "REGIO": "Dél-Alföld",
      "VARMEGYE": "Békés",
      "TELEPULES": "Békéscsaba",
      "IRSZ": "5600",
      "MIGRALT": false,
      "MERET": 2100,
      "MEGJEGYZES": "Regionális elosztóközpont"
    },
    {
      "AZONOSITO": "SITE-075-KM",
      "MEGNEVEZES": "Kecskeméti Ipari Park",
      "MEGNEVEZES_ANGOL": "Kecskemet Industrial Park",
      "TIPUS": "Gyártóüzem",
      "REGIO": "Dél-Alföld",
      "VARMEGYE": "Bács-Kiskun",
      "TELEPULES": "Kecskemét",
      "IRSZ": "6000",
      "MIGRALT": false,
      "MERET": 3700,
      "MEGJEGYZES": "Autóipari termékek gyártása"
    },
    {
      "AZONOSITO": "SITE-076-NY",
      "MEGNEVEZES": "Nyíregyházi Irodaház",
      "MEGNEVEZES_ANGOL": "Nyiregyhaza Office Building",
      "TIPUS": "Iroda",
      "REGIO": "Észak-Alföld",
      "VARMEGYE": "Szabolcs-Szatmár-Bereg",
      "TELEPULES": "Nyíregyháza",
      "IRSZ": "4400",
      "MIGRALT": false,
      "MERET": 720,
      "MEGJEGYZES": "Modern irodaház a belvárosban"
    },
    {
      "AZONOSITO": "SITE-077-GO",
      "MEGNEVEZES": "Gödöllői Logisztikai Központ",
      "MEGNEVEZES_ANGOL": "Godollo Logistics Center",
      "TIPUS": "Logisztikai központ",
      "REGIO": "Közép-Magyarország",
      "VARMEGYE": "Pest",
      "TELEPULES": "Gödöllő",
      "IRSZ": "2100",
      "MIGRALT": false,
      "MERET": 2000,
      "MEGJEGYZES": "Mezőgazdasági termékek elosztóközpontja"
    },
    {
      "AZONOSITO": "SITE-078-SE",
      "MEGNEVEZES": "Szentendrei Ipari Park",
      "MEGNEVEZES_ANGOL": "Szentendre Industrial Park",
      "TIPUS": "Gyártóüzem",
      "REGIO": "Közép-Magyarország",
      "VARMEGYE": "Pest",
      "TELEPULES": "Szentendre",
      "IRSZ": "2000",
      "MIGRALT": false,
      "MERET": 2300,
      "MEGJEGYZES": "Művészeti termékek gyártása"
    },
    {
      "AZONOSITO": "SITE-079-HS",
      "MEGNEVEZES": "Hajdúszoboszlói Raktárbázis",
      "MEGNEVEZES_ANGOL": "Hajduszoboszlo Warehouse Base",
      "TIPUS": "Raktár",
      "REGIO": "Észak-Alföld",
      "VARMEGYE": "Hajdú-Bihar",
      "TELEPULES": "Hajdúszoboszló",
      "IRSZ": "4200",
      "MIGRALT": false,
      "MERET": 1200,
      "MEGJEGYZES": "Turisztikai termékek raktára"
    },
    {
      "AZONOSITO": "SITE-080-HM",
      "MEGNEVEZES": "Hódmezővásárhelyi Logisztikai Központ",
      "MEGNEVEZES_ANGOL": "Hodmezovasarhely Logistics Center",
      "TIPUS": "Logisztikai központ",
      "REGIO": "Dél-Alföld",
      "VARMEGYE": "Csongrád-Csanád",
      "TELEPULES": "Hódmezővásárhely",
      "IRSZ": "6800",
      "MIGRALT": false,
      "MERET": 2000,
      "MEGJEGYZES": "Kerámiaipari termékek elosztóközpontja"
    },
    {
      "AZONOSITO": "SITE-081-MO",
      "MEGNEVEZES": "Mohácsi Ipari Park",
      "MEGNEVEZES_ANGOL": "Mohacs Industrial Park",
      "TIPUS": "Gyártóüzem",
      "REGIO": "Dél-Dunántúl",
      "VARMEGYE": "Baranya",
      "TELEPULES": "Mohács",
      "IRSZ": "7700",
      "MIGRALT": false,
      "MERET": 2500,
      "MEGJEGYZES": "Faipari termékek gyártása"
    },
    {
      "AZONOSITO": "SITE-082-KB",
      "MEGNEVEZES": "Kazincbarcikai Logisztikai Központ",
      "MEGNEVEZES_ANGOL": "Kazincbarcika Logistics Center",
      "TIPUS": "Logisztikai központ",
      "REGIO": "Észak-Magyarország",
      "VARMEGYE": "Borsod-Abaúj-Zemplén",
      "TELEPULES": "Kazincbarcika",
      "IRSZ": "3700",
      "MIGRALT": false,
      "MERET": 1900,
      "MEGJEGYZES": "Vegyipari termékek elosztóközpontja"
    },
    {
      "AZONOSITO": "SITE-083-SO",
      "MEGNEVEZES": "Soproni Raktárbázis",
      "MEGNEVEZES_ANGOL": "Sopron Warehouse Base",
      "TIPUS": "Raktár",
      "REGIO": "Nyugat-Dunántúl",
      "VARMEGYE": "Győr-Moson-Sopron",
      "TELEPULES": "Sopron",
      "IRSZ": "9400",
      "MIGRALT": false,
      "MERET": 1400,
      "MEGJEGYZES": "Faipari termékek raktára"
    },
    {
      "AZONOSITO": "SITE-084-BP",
      "MEGNEVEZES": "Budaörsi Ipari Park",
      "MEGNEVEZES_ANGOL": "Budaors Industrial Park",
      "TIPUS": "Gyártóüzem",
      "REGIO": "Közép-Magyarország",
      "VARMEGYE": "Pest",
      "TELEPULES": "Budaörs",
      "IRSZ": "2040",
      "MIGRALT": false,
      "MERET": 2700,
      "MEGJEGYZES": "Elektronikai termékek gyártása"
    },
    {
      "AZONOSITO": "SITE-085-DB",
      "MEGNEVEZES": "Debreceni Raktárbázis",
      "MEGNEVEZES_ANGOL": "Debrecen Warehouse Base",
      "TIPUS": "Raktár",
      "REGIO": "Észak-Alföld",
      "VARMEGYE": "Hajdú-Bihar",
      "TELEPULES": "Debrecen",
      "IRSZ": "4032",
      "MIGRALT": false,
      "MERET": 1650,
      "MEGJEGYZES": "Gyógyszeripari termékek raktára"
    },
    {
      "AZONOSITO": "SITE-086-MI",
      "MEGNEVEZES": "Miskolci Irodaház",
      "MEGNEVEZES_ANGOL": "Miskolc Office Building",
      "TIPUS": "Iroda",
      "REGIO": "Észak-Magyarország",
      "VARMEGYE": "Borsod-Abaúj-Zemplén",
      "TELEPULES": "Miskolc",
      "IRSZ": "3525",
      "MIGRALT": false,
      "MERET": 850,
      "MEGJEGYZES": "Modern irodaház a belvárosban"
    },
    {
      "AZONOSITO": "SITE-087-PE",
      "MEGNEVEZES": "Pécsi Logisztikai Központ",
      "MEGNEVEZES_ANGOL": "Pecs Logistics Center",
      "TIPUS": "Logisztikai központ",
      "REGIO": "Dél-Dunántúl",
      "VARMEGYE": "Baranya",
      "TELEPULES": "Pécs",
      "IRSZ": "7632",
      "MIGRALT": false,
      "MERET": 2200,
      "MEGJEGYZES": "Regionális elosztóközpont"
    }
  ]
}
